exoclasma_note/__init__.py
exoclasma_note/exoclasma_note.py
exoclasma_note/config/AnnoFit_config.json
exoclasma_note/config/DaemonicPipeline_config.json
exoclasma_note/db/HGMD.tsv
exoclasma_note/db/Problematic_Regions/ENCODE_Blacklist
exoclasma_note/db/Problematic_Regions/GIAB_AlignProblem
exoclasma_note/db/Problematic_Regions/GIAB_AlleleImbalance
exoclasma_note/db/Problematic_Regions/GIAB_CallConflict
exoclasma_note/db/Problematic_Regions/GIAB_FilterSSE
exoclasma_note/db/Problematic_Regions/GIAB_GenotypeConflict
exoclasma_note/db/Problematic_Regions/GIAB_QualityIssue
exoclasma_note/db/Problematic_Regions/GIAB_merged_GenotypeConflict
exoclasma_note/db/Problematic_Regions/NCBI_NGS_DeadZone
exoclasma_note/db/Problematic_Regions/NCBI_NGS_HighStringency
exoclasma_note/db/Problematic_Regions/NCBI_NGS_LowStringency
exoclasma_note/db/Problematic_Regions/NCBI_Sanger_DeadZone
exoclasma_note/db/Problematic_Regions/UCSC_UnusualRegions
exoclasma_note-0.9.0.dist-info/METADATA
exoclasma_note-0.9.0.dist-info/WHEEL
exoclasma_note-0.9.0.dist-info/entry_points.txt
exoclasma_note-0.9.0.dist-info/licenses/LICENSE
exoclasma_note-0.9.0.dist-info/RECORD
